[
    {
        "順位": "1",
        "駅名": "新宿",
        "乗降客数": "1205116"
    },
    {
        "順位": "2",
        "駅名": "渋谷",
        "乗降客数": "936944"
    },
    {
        "順位": "3",
        "駅名": "池袋",
        "乗降客数": "917582"
    },
    {
        "順位": "4",
        "駅名": "梅田",
        "乗降客数": "402947"
    },
    {
        "順位": "5",
        "駅名": "大阪",
        "乗降客数": "694156"
    },
    {
        "順位": "6",
        "駅名": "東京",
        "乗降客数": "693316"
    },
    {
        "順位": "7",
        "駅名": "横浜",
        "乗降客数": "681072"
    },
    {
        "順位": "8",
        "駅名": "品川",
        "乗降客数": "497300"
    },
    {
        "順位": "9",
        "駅名": "大宮",
        "乗降客数": "452498"
    },
    {
        "順位": "10",
        "駅名": "新宿御苑前",
        "乗降客数": "422861"
    },
    {
        "順位": "11",
        "駅名": "新橋",
        "乗降客数": "386488"
    },
    {
        "順位": "12",
        "駅名": "北千住",
        "乗降客数": "382081"
    },
    {
        "順位": "13",
        "駅名": "秋葉原",
        "乗降客数": "381012"
    },
    {
        "順位": "14",
        "駅名": "名古屋",
        "乗降客数": "354486"
    },
    {
        "順位": "15",
        "駅名": "川崎",
        "乗降客数": "351752"
    },
    {
        "順位": "16",
        "駅名": "西船橋",
        "乗降客数": "350592"
    },
    {
        "順位": "17",
        "駅名": "綾瀬",
        "乗降客数": "349331"
    },
    {
        "順位": "18",
        "駅名": "高田馬場",
        "乗降客数": "334530"
    },
    {
        "順位": "19",
        "駅名": "京都",
        "乗降客数": "298812"
    },
    {
        "順位": "20",
        "駅名": "難波",
        "乗降客数": "298803"
    },
    {
        "順位": "21",
        "駅名": "上野",
        "乗降客数": "295554"
    },
    {
        "順位": "22",
        "駅名": "立川",
        "乗降客数": "288914"
    },
    {
        "順位": "23",
        "駅名": "小竹向原",
        "乗降客数": "281480"
    },
    {
        "順位": "24",
        "駅名": "大手町",
        "乗降客数": "277497"
    },
    {
        "順位": "25",
        "駅名": "天王寺",
        "乗降客数": "255496"
    },
    {
        "順位": "26",
        "駅名": "名鉄名古屋",
        "乗降客数": "255163"
    },
    {
        "順位": "27",
        "駅名": "町田",
        "乗降客数": "246459"
    },
    {
        "順位": "28",
        "駅名": "中野",
        "乗降客数": "239692"
    },
    {
        "順位": "29",
        "駅名": "船橋",
        "乗降客数": "238460"
    },
    {
        "順位": "30",
        "駅名": "吉祥寺",
        "乗降客数": "237730"
    },
    {
        "順位": "31",
        "駅名": "代々木上原",
        "乗降客数": "237023"
    },
    {
        "順位": "32",
        "駅名": "大崎",
        "乗降客数": "236978"
    },
    {
        "順位": "33",
        "駅名": "九段下",
        "乗降客数": "236661"
    },
    {
        "順位": "34",
        "駅名": "有楽町",
        "乗降客数": "233476"
    },
    {
        "順位": "35",
        "駅名": "蒲田",
        "乗降客数": "227292"
    },
    {
        "順位": "36",
        "駅名": "浜松町",
        "乗降客数": "225734"
    },
    {
        "順位": "37",
        "駅名": "恵比寿",
        "乗降客数": "225204"
    },
    {
        "順位": "38",
        "駅名": "目黒",
        "乗降客数": "223329"
    },
    {
        "順位": "39",
        "駅名": "三ノ宮",
        "乗降客数": "219532"
    },
    {
        "順位": "40",
        "駅名": "田町",
        "乗降客数": "218592"
    },
    {
        "順位": "41",
        "駅名": "京橋(大阪)",
        "乗降客数": "218388"
    },
    {
        "順位": "42",
        "駅名": "柏",
        "乗降客数": "217640"
    },
    {
        "順位": "43",
        "駅名": "博多",
        "乗降客数": "216766"
    },
    {
        "順位": "44",
        "駅名": "五反田",
        "乗降客数": "204974"
    },
    {
        "順位": "45",
        "駅名": "武蔵小杉",
        "乗降客数": "199938"
    },
    {
        "順位": "46",
        "駅名": "藤沢",
        "乗降客数": "191714"
    },
    {
        "順位": "47",
        "駅名": "千葉",
        "乗降客数": "189728"
    },
    {
        "順位": "48",
        "駅名": "淀屋橋",
        "乗降客数": "189507"
    },
    {
        "順位": "49",
        "駅名": "国分寺",
        "乗降客数": "189468"
    },
    {
        "順位": "50",
        "駅名": "押上",
        "乗降客数": "188833"
    },
    {
        "順位": "51",
        "駅名": "銀座",
        "乗降客数": "188770"
    },
    {
        "順位": "52",
        "駅名": "本町",
        "乗降客数": "187469"
    },
    {
        "順位": "53",
        "駅名": "戸塚",
        "乗降客数": "186036"
    },
    {
        "順位": "54",
        "駅名": "日暮里",
        "乗降客数": "185568"
    },
    {
        "順位": "55",
        "駅名": "溝の口",
        "乗降客数": "183756"
    },
    {
        "順位": "56",
        "駅名": "栄",
        "乗降客数": "183400"
    },
    {
        "順位": "57",
        "駅名": "日吉",
        "乗降客数": "179320"
    },
    {
        "順位": "58",
        "駅名": "豊洲",
        "乗降客数": "176881"
    },
    {
        "順位": "59",
        "駅名": "錦糸町",
        "乗降客数": "175180"
    },
    {
        "順位": "60",
        "駅名": "赤羽",
        "乗降客数": "173036"
    },
    {
        "順位": "61",
        "駅名": "泉岳寺",
        "乗降客数": "170671"
    },
    {
        "順位": "62",
        "駅名": "津田沼",
        "乗降客数": "170144"
    },
    {
        "順位": "63",
        "駅名": "松戸",
        "乗降客数": "169190"
    },
    {
        "順位": "64",
        "駅名": "西日暮里",
        "乗降客数": "168512"
    },
    {
        "順位": "65",
        "駅名": "大船",
        "乗降客数": "168498"
    },
    {
        "順位": "66",
        "駅名": "浦和",
        "乗降客数": "168232"
    },
    {
        "順位": "67",
        "駅名": "鶴橋",
        "乗降客数": "168208"
    },
    {
        "順位": "68",
        "駅名": "神田",
        "乗降客数": "162092"
    },
    {
        "順位": "69",
        "駅名": "御茶ノ水",
        "乗降客数": "160278"
    },
    {
        "順位": "70",
        "駅名": "四ツ谷",
        "乗降客数": "159008"
    },
    {
        "順位": "71",
        "駅名": "三鷹",
        "乗降客数": "158830"
    },
    {
        "順位": "72",
        "駅名": "仙台",
        "乗降客数": "158150"
    },
    {
        "順位": "73",
        "駅名": "中目黒",
        "乗降客数": "155782"
    },
    {
        "順位": "74",
        "駅名": "大井町",
        "乗降客数": "154926"
    },
    {
        "順位": "75",
        "駅名": "札幌",
        "乗降客数": "154528"
    },
    {
        "順位": "76",
        "駅名": "表参道",
        "乗降客数": "154173"
    },
    {
        "順位": "77",
        "駅名": "金山",
        "乗降客数": "153073"
    },
    {
        "順位": "78",
        "駅名": "和光市",
        "乗降客数": "152949"
    },
    {
        "順位": "79",
        "駅名": "荻窪",
        "乗降客数": "152460"
    },
    {
        "順位": "80",
        "駅名": "さっぽろ",
        "乗降客数": "147770"
    },
    {
        "順位": "81",
        "駅名": "登戸",
        "乗降客数": "146926"
    },
    {
        "順位": "82",
        "駅名": "日本橋（東京）",
        "乗降客数": "146916"
    },
    {
        "順位": "83",
        "駅名": "東梅田",
        "乗降客数": "146623"
    },
    {
        "順位": "84",
        "駅名": "武蔵溝ノ口",
        "乗降客数": "145660"
    },
    {
        "順位": "85",
        "駅名": "大森",
        "乗降客数": "145136"
    },
    {
        "順位": "86",
        "駅名": "八王子",
        "乗降客数": "144202"
    },
    {
        "順位": "87",
        "駅名": "朝霞台",
        "乗降客数": "143856"
    },
    {
        "順位": "88",
        "駅名": "川口",
        "乗降客数": "142708"
    },
    {
        "順位": "89",
        "駅名": "大通",
        "乗降客数": "142592"
    },
    {
        "順位": "90",
        "駅名": "大阪阿部野橋",
        "乗降客数": "140475"
    },
    {
        "順位": "91",
        "駅名": "大阪難波",
        "乗降客数": "138771"
    },
    {
        "順位": "92",
        "駅名": "飯田橋",
        "乗降客数": "138426"
    },
    {
        "順位": "93",
        "駅名": "南越谷",
        "乗降客数": "135630"
    },
    {
        "順位": "94",
        "駅名": "西武新宿",
        "乗降客数": "135139"
    },
    {
        "順位": "95",
        "駅名": "新越谷",
        "乗降客数": "134580"
    },
    {
        "順位": "96",
        "駅名": "二子玉川",
        "乗降客数": "133086"
    },
    {
        "順位": "97",
        "駅名": "新小岩",
        "乗降客数": "133070"
    },
    {
        "順位": "98",
        "駅名": "新大阪",
        "乗降客数": "132965"
    },
    {
        "順位": "99",
        "駅名": "鶴見",
        "乗降客数": "132048"
    },
    {
        "順位": "100",
        "駅名": "桜木町",
        "乗降客数": "129396"
    },
    {
        "順位": "101",
        "駅名": "新宿三丁目",
        "乗降客数": "129191"
    },
    {
        "順位": "102",
        "駅名": "心斎橋",
        "乗降客数": "128279"
    },
    {
        "順位": "103",
        "駅名": "舞浜",
        "乗降客数": "127812"
    },
    {
        "順位": "104",
        "駅名": "北朝霞",
        "乗降客数": "127052"
    },
    {
        "順位": "105",
        "駅名": "巣鴨",
        "乗降客数": "126844"
    },
    {
        "順位": "106",
        "駅名": "広島",
        "乗降客数": "126430"
    },
    {
        "順位": "107",
        "駅名": "水道橋",
        "乗降客数": "125776"
    },
    {
        "順位": "108",
        "駅名": "自由が丘",
        "乗降客数": "125005"
    },
    {
        "順位": "109",
        "駅名": "三軒茶屋",
        "乗降客数": "124990"
    },
    {
        "順位": "110",
        "駅名": "海老名",
        "乗降客数": "123222"
    },
    {
        "順位": "111",
        "駅名": "上大岡",
        "乗降客数": "122376"
    },
    {
        "順位": "112",
        "駅名": "長津田",
        "乗降客数": "121815"
    },
    {
        "順位": "113",
        "駅名": "霞ヶ関",
        "乗降客数": "121447"
    },
    {
        "順位": "114",
        "駅名": "新木場",
        "乗降客数": "120884"
    },
    {
        "順位": "115",
        "駅名": "岡山",
        "乗降客数": "119262"
    },
    {
        "順位": "116",
        "駅名": "天神",
        "乗降客数": "118279"
    },
    {
        "順位": "117",
        "駅名": "神保町",
        "乗降客数": "117659"
    },
    {
        "順位": "118",
        "駅名": "武蔵境",
        "乗降客数": "116492"
    },
    {
        "順位": "119",
        "駅名": "市ヶ谷",
        "乗降客数": "116190"
    },
    {
        "順位": "120",
        "駅名": "新今宮",
        "乗降客数": "115498"
    },
    {
        "順位": "121",
        "駅名": "原宿",
        "乗降客数": "115448"
    },
    {
        "順位": "122",
        "駅名": "本厚木",
        "乗降客数": "114922"
    },
    {
        "順位": "123",
        "駅名": "橋本",
        "乗降客数": "113998"
    },
    {
        "順位": "124",
        "駅名": "京急川崎",
        "乗降客数": "112923"
    },
    {
        "順位": "125",
        "駅名": "あざみ野",
        "乗降客数": "112644"
    },
    {
        "順位": "126",
        "駅名": "高槻",
        "乗降客数": "112320"
    },
    {
        "順位": "127",
        "駅名": "三宮",
        "乗降客数": "112156"
    },
    {
        "順位": "128",
        "駅名": "下北沢",
        "乗降客数": "112116"
    },
    {
        "順位": "129",
        "駅名": "御徒町",
        "乗降客数": "111742"
    },
    {
        "順位": "130",
        "駅名": "小岩",
        "乗降客数": "111126"
    },
    {
        "順位": "131",
        "駅名": "菊名",
        "乗降客数": "111040"
    },
    {
        "順位": "132",
        "駅名": "練馬",
        "乗降客数": "110966"
    },
    {
        "順位": "133",
        "駅名": "相模大野",
        "乗降客数": "110249"
    },
    {
        "順位": "134",
        "駅名": "川越",
        "乗降客数": "110102"
    },
    {
        "順位": "135",
        "駅名": "西鉄福岡（天神）",
        "乗降客数": "109641"
    },
    {
        "順位": "136",
        "駅名": "調布",
        "乗降客数": "109110"
    },
    {
        "順位": "137",
        "駅名": "新百合ヶ丘",
        "乗降客数": "108661"
    },
    {
        "順位": "138",
        "駅名": "王子",
        "乗降客数": "108168"
    },
    {
        "順位": "139",
        "駅名": "大和",
        "乗降客数": "107131"
    },
    {
        "順位": "140",
        "駅名": "神戸",
        "乗降客数": "107126"
    },
    {
        "順位": "141",
        "駅名": "武蔵小金井",
        "乗降客数": "106684"
    },
    {
        "順位": "142",
        "駅名": "辻堂",
        "乗降客数": "105146"
    },
    {
        "順位": "143",
        "駅名": "市川",
        "乗降客数": "104824"
    },
    {
        "順位": "144",
        "駅名": "平塚",
        "乗降客数": "104550"
    },
    {
        "順位": "145",
        "駅名": "海浜幕張",
        "乗降客数": "104116"
    },
    {
        "順位": "146",
        "駅名": "本八幡",
        "乗降客数": "103610"
    },
    {
        "順位": "147",
        "駅名": "東陽町",
        "乗降客数": "102996"
    },
    {
        "順位": "148",
        "駅名": "蕨",
        "乗降客数": "102934"
    },
    {
        "順位": "149",
        "駅名": "新横浜",
        "乗降客数": "102884"
    },
    {
        "順位": "150",
        "駅名": "南浦和",
        "乗降客数": "102616"
    },
    {
        "順位": "151",
        "駅名": "代々木",
        "乗降客数": "102192"
    },
    {
        "順位": "152",
        "駅名": "西川口",
        "乗降客数": "100892"
    },
    {
        "順位": "153",
        "駅名": "三越前",
        "乗降客数": "100581"
    },
    {
        "順位": "154",
        "駅名": "亀戸",
        "乗降客数": "99236"
    },
    {
        "順位": "155",
        "駅名": "静岡",
        "乗降客数": "99069"
    },
    {
        "順位": "156",
        "駅名": "堺筋本町",
        "乗降客数": "99019"
    },
    {
        "順位": "157",
        "駅名": "神戸三宮",
        "乗降客数": "98937"
    },
    {
        "順位": "158",
        "駅名": "さいたま新都心",
        "乗降客数": "98664"
    },
    {
        "順位": "159",
        "駅名": "東戸塚",
        "乗降客数": "97832"
    },
    {
        "順位": "160",
        "駅名": "茅ヶ崎",
        "乗降客数": "97064"
    },
    {
        "順位": "161",
        "駅名": "大塚",
        "乗降客数": "97018"
    },
    {
        "順位": "162",
        "駅名": "西梅田",
        "乗降客数": "96846"
    },
    {
        "順位": "163",
        "駅名": "馬喰横山",
        "乗降客数": "96253"
    },
    {
        "順位": "164",
        "駅名": "所沢",
        "乗降客数": "95294"
    },
    {
        "順位": "165",
        "駅名": "六本木",
        "乗降客数": "94895"
    },
    {
        "順位": "166",
        "駅名": "新浦安",
        "乗降客数": "94764"
    },
    {
        "順位": "167",
        "駅名": "茅場町",
        "乗降客数": "94538"
    },
    {
        "順位": "168",
        "駅名": "中央林間",
        "乗降客数": "93412"
    },
    {
        "順位": "169",
        "駅名": "武蔵浦和",
        "乗降客数": "93186"
    },
    {
        "順位": "170",
        "駅名": "江坂",
        "乗降客数": "93022"
    },
    {
        "順位": "171",
        "駅名": "烏丸御池",
        "乗降客数": "92346"
    },
    {
        "順位": "172",
        "駅名": "門前仲町",
        "乗降客数": "92275"
    },
    {
        "順位": "173",
        "駅名": "青葉台",
        "乗降客数": "91922"
    },
    {
        "順位": "174",
        "駅名": "姫路",
        "乗降客数": "91574"
    },
    {
        "順位": "175",
        "駅名": "金町",
        "乗降客数": "91280"
    },
    {
        "順位": "176",
        "駅名": "明石",
        "乗降客数": "91148"
    },
    {
        "順位": "177",
        "駅名": "国立",
        "乗降客数": "90396"
    },
    {
        "順位": "178",
        "駅名": "志木",
        "乗降客数": "90290"
    },
    {
        "順位": "179",
        "駅名": "北浦和",
        "乗降客数": "90170"
    },
    {
        "順位": "180",
        "駅名": "京成高砂",
        "乗降客数": "90137"
    },
    {
        "順位": "181",
        "駅名": "羽田空港第1・第2ターミナル",
        "乗降客数": "89728"
    },
    {
        "順位": "182",
        "駅名": "八丁堀",
        "乗降客数": "89641"
    },
    {
        "順位": "183",
        "駅名": "浅草橋",
        "乗降客数": "89608"
    },
    {
        "順位": "184",
        "駅名": "関内",
        "乗降客数": "89568"
    },
    {
        "順位": "185",
        "駅名": "葛西",
        "乗降客数": "89311"
    },
    {
        "順位": "186",
        "駅名": "近鉄名古屋",
        "乗降客数": "89232"
    },
    {
        "順位": "187",
        "駅名": "後楽園",
        "乗降客数": "89048"
    },
    {
        "順位": "188",
        "駅名": "西葛西",
        "乗降客数": "88528"
    },
    {
        "順位": "189",
        "駅名": "四条",
        "乗降客数": "88018"
    },
    {
        "順位": "190",
        "駅名": "綱島",
        "乗降客数": "87731"
    },
    {
        "順位": "191",
        "駅名": "西宮北口",
        "乗降客数": "87145"
    },
    {
        "順位": "192",
        "駅名": "新大久保",
        "乗降客数": "87104"
    },
    {
        "順位": "193",
        "駅名": "高円寺",
        "乗降客数": "86592"
    },
    {
        "順位": "194",
        "駅名": "明治神宮前",
        "乗降客数": "86222"
    },
    {
        "順位": "195",
        "駅名": "稲毛",
        "乗降客数": "86156"
    },
    {
        "順位": "196",
        "駅名": "三田",
        "乗降客数": "86130"
    },
    {
        "順位": "197",
        "駅名": "日比谷",
        "乗降客数": "85949"
    },
    {
        "順位": "198",
        "駅名": "伏見",
        "乗降客数": "85592"
    },
    {
        "順位": "199",
        "駅名": "浅草",
        "乗降客数": "84355"
    },
    {
        "順位": "200",
        "駅名": "姪浜",
        "乗降客数": "83991"
    },
    {
        "順位": "201",
        "駅名": "尼崎",
        "乗降客数": "83442"
    },
    {
        "順位": "202",
        "駅名": "茨木",
        "乗降客数": "83164"
    },
    {
        "順位": "203",
        "駅名": "京成船橋",
        "乗降客数": "82828"
    },
    {
        "順位": "204",
        "駅名": "湘南台",
        "乗降客数": "82372"
    },
    {
        "順位": "205",
        "駅名": "赤羽岩淵",
        "乗降客数": "82352"
    },
    {
        "順位": "206",
        "駅名": "大門",
        "乗降客数": "82083"
    },
    {
        "順位": "207",
        "駅名": "駒込",
        "乗降客数": "81812"
    },
    {
        "順位": "208",
        "駅名": "青山一丁目",
        "乗降客数": "81621"
    },
    {
        "順位": "209",
        "駅名": "北新地",
        "乗降客数": "81108"
    },
    {
        "順位": "210",
        "駅名": "虎ノ門",
        "乗降客数": "80864"
    },
    {
        "順位": "211",
        "駅名": "分倍河原",
        "乗降客数": "80296"
    },
    {
        "順位": "212",
        "駅名": "谷町四丁目",
        "乗降客数": "79391"
    },
    {
        "順位": "213",
        "駅名": "西荻窪",
        "乗降客数": "79272"
    },
    {
        "順位": "214",
        "駅名": "天満橋",
        "乗降客数": "79050"
    },
    {
        "順位": "215",
        "駅名": "赤坂見附",
        "乗降客数": "78766"
    },
    {
        "順位": "216",
        "駅名": "草加",
        "乗降客数": "78019"
    },
    {
        "順位": "217",
        "駅名": "豊橋",
        "乗降客数": "77610"
    },
    {
        "順位": "218",
        "駅名": "新御茶ノ水",
        "乗降客数": "77610"
    },
    {
        "順位": "219",
        "駅名": "千里中央",
        "乗降客数": "76572"
    },
    {
        "順位": "220",
        "駅名": "阿佐ヶ谷",
        "乗降客数": "76512"
    },
    {
        "順位": "221",
        "駅名": "鎌倉",
        "乗降客数": "76464"
    },
    {
        "順位": "222",
        "駅名": "府中",
        "乗降客数": "75924"
    },
    {
        "順位": "223",
        "駅名": "モノレール浜松町",
        "乗降客数": "75646"
    },
    {
        "順位": "224",
        "駅名": "大泉学園",
        "乗降客数": "75513"
    },
    {
        "順位": "225",
        "駅名": "経堂",
        "乗降客数": "75323"
    },
    {
        "順位": "226",
        "駅名": "流山おおたかの森",
        "乗降客数": "75200"
    },
    {
        "順位": "227",
        "駅名": "成城学園前",
        "乗降客数": "74920"
    },
    {
        "順位": "228",
        "駅名": "亀有",
        "乗降客数": "74798"
    },
    {
        "順位": "229",
        "駅名": "勝どき",
        "乗降客数": "74776"
    },
    {
        "順位": "230",
        "駅名": "田端",
        "乗降客数": "74582"
    },
    {
        "順位": "231",
        "駅名": "京王多摩センター",
        "乗降客数": "74516"
    },
    {
        "順位": "232",
        "駅名": "南森町",
        "乗降客数": "74209"
    },
    {
        "順位": "233",
        "駅名": "千歳烏山",
        "乗降客数": "74178"
    },
    {
        "順位": "234",
        "駅名": "たまプラーザ",
        "乗降客数": "73901"
    },
    {
        "順位": "235",
        "駅名": "みなとみらい",
        "乗降客数": "73680"
    },
    {
        "順位": "236",
        "駅名": "二俣川",
        "乗降客数": "72905"
    },
    {
        "順位": "237",
        "駅名": "上尾",
        "乗降客数": "72670"
    },
    {
        "順位": "238",
        "駅名": "神谷町",
        "乗降客数": "72423"
    },
    {
        "順位": "239",
        "駅名": "中山",
        "乗降客数": "72192"
    },
    {
        "順位": "240",
        "駅名": "秋津",
        "乗降客数": "71805"
    },
    {
        "順位": "241",
        "駅名": "石神井公園",
        "乗降客数": "71474"
    },
    {
        "順位": "242",
        "駅名": "浦安",
        "乗降客数": "71398"
    },
    {
        "順位": "243",
        "駅名": "東川口",
        "乗降客数": "70092"
    },
    {
        "順位": "244",
        "駅名": "早稲田",
        "乗降客数": "70006"
    },
    {
        "順位": "245",
        "駅名": "新秋津",
        "乗降客数": "69908"
    },
    {
        "順位": "246",
        "駅名": "西新宿",
        "乗降客数": "69891"
    },
    {
        "順位": "247",
        "駅名": "南流山",
        "乗降客数": "69700"
    },
    {
        "順位": "248",
        "駅名": "枚方市",
        "乗降客数": "69274"
    },
    {
        "順位": "249",
        "駅名": "東中野",
        "乗降客数": "68824"
    },
    {
        "順位": "250",
        "駅名": "東日本橋",
        "乗降客数": "67896"
    },
    {
        "順位": "251",
        "駅名": "学芸大学",
        "乗降客数": "67776"
    },
    {
        "順位": "252",
        "駅名": "東銀座",
        "乗降客数": "67709"
    },
    {
        "順位": "253",
        "駅名": "駒沢大学",
        "乗降客数": "67494"
    },
    {
        "順位": "254",
        "駅名": "新松戸",
        "乗降客数": "67350"
    },
    {
        "順位": "255",
        "駅名": "仙川",
        "乗降客数": "67190"
    },
    {
        "順位": "256",
        "駅名": "天下茶屋",
        "乗降客数": "67025"
    },
    {
        "順位": "257",
        "駅名": "笹塚",
        "乗降客数": "66646"
    },
    {
        "順位": "258",
        "駅名": "赤坂",
        "乗降客数": "66289"
    },
    {
        "順位": "259",
        "駅名": "烏丸",
        "乗降客数": "66086"
    },
    {
        "順位": "260",
        "駅名": "半蔵門",
        "乗降客数": "66059"
    },
    {
        "順位": "261",
        "駅名": "永田町",
        "乗降客数": "66041"
    },
    {
        "順位": "262",
        "駅名": "中野坂上",
        "乗降客数": "65946"
    },
    {
        "順位": "263",
        "駅名": "淵野辺",
        "乗降客数": "65502"
    },
    {
        "順位": "264",
        "駅名": "茗荷谷",
        "乗降客数": "64833"
    },
    {
        "順位": "265",
        "駅名": "谷町九丁目",
        "乗降客数": "64781"
    },
    {
        "順位": "266",
        "駅名": "木場",
        "乗降客数": "64776"
    },
    {
        "順位": "267",
        "駅名": "外苑前",
        "乗降客数": "64750"
    },
    {
        "順位": "268",
        "駅名": "十条",
        "乗降客数": "64214"
    },
    {
        "順位": "269",
        "駅名": "鴨居",
        "乗降客数": "64204"
    },
    {
        "順位": "270",
        "駅名": "東神奈川",
        "乗降客数": "64020"
    },
    {
        "順位": "271",
        "駅名": "新杉田",
        "乗降客数": "63944"
    },
    {
        "順位": "272",
        "駅名": "田無",
        "乗降客数": "63936"
    },
    {
        "順位": "273",
        "駅名": "中百舌鳥",
        "乗降客数": "63852"
    },
    {
        "順位": "274",
        "駅名": "ひばりヶ丘",
        "乗降客数": "63812"
    },
    {
        "順位": "275",
        "駅名": "森下",
        "乗降客数": "63689"
    },
    {
        "順位": "276",
        "駅名": "武蔵新城",
        "乗降客数": "63470"
    },
    {
        "順位": "277",
        "駅名": "溜池山王",
        "乗降客数": "63392"
    },
    {
        "順位": "278",
        "駅名": "人形町",
        "乗降客数": "63201"
    },
    {
        "順位": "279",
        "駅名": "大阪上本町",
        "乗降客数": "63121"
    },
    {
        "順位": "280",
        "駅名": "竹ノ塚",
        "乗降客数": "63092"
    },
    {
        "順位": "281",
        "駅名": "住吉",
        "乗降客数": "63078"
    },
    {
        "順位": "282",
        "駅名": "両国",
        "乗降客数": "62602"
    },
    {
        "順位": "283",
        "駅名": "弁天町",
        "乗降客数": "62602"
    },
    {
        "順位": "284",
        "駅名": "宇都宮",
        "乗降客数": "62482"
    },
    {
        "順位": "285",
        "駅名": "小川町",
        "乗降客数": "62423"
    },
    {
        "順位": "286",
        "駅名": "北浜",
        "乗降客数": "62161"
    },
    {
        "順位": "287",
        "駅名": "桜新町",
        "乗降客数": "61954"
    },
    {
        "順位": "288",
        "駅名": "戸田公園",
        "乗降客数": "61830"
    },
    {
        "順位": "289",
        "駅名": "山科",
        "乗降客数": "61726"
    },
    {
        "順位": "290",
        "駅名": "目白",
        "乗降客数": "61680"
    },
    {
        "順位": "291",
        "駅名": "朝霞",
        "乗降客数": "61638"
    },
    {
        "順位": "292",
        "駅名": "日本橋（大阪）",
        "乗降客数": "61347"
    },
    {
        "順位": "293",
        "駅名": "春日部",
        "乗降客数": "61279"
    },
    {
        "順位": "294",
        "駅名": "ユニバーサルシティ",
        "乗降客数": "61230"
    },
    {
        "順位": "295",
        "駅名": "小倉",
        "乗降客数": "60594"
    },
    {
        "順位": "296",
        "駅名": "春日",
        "乗降客数": "60591"
    },
    {
        "順位": "297",
        "駅名": "月島",
        "乗降客数": "60498"
    },
    {
        "順位": "298",
        "駅名": "東大宮",
        "乗降客数": "60468"
    },
    {
        "順位": "299",
        "駅名": "久喜",
        "乗降客数": "60450"
    },
    {
        "順位": "300",
        "駅名": "用賀",
        "乗降客数": "60422"
    },
    {
        "順位": "301",
        "駅名": "浜松",
        "乗降客数": "60382"
    },
    {
        "順位": "302",
        "駅名": "大曽根",
        "乗降客数": "60306"
    },
    {
        "順位": "303",
        "駅名": "板橋",
        "乗降客数": "60236"
    },
    {
        "順位": "304",
        "駅名": "元町",
        "乗降客数": "60216"
    },
    {
        "順位": "305",
        "駅名": "六本木一丁目",
        "乗降客数": "60048"
    },
    {
        "順位": "306",
        "駅名": "新潟",
        "乗降客数": "59538"
    },
    {
        "順位": "307",
        "駅名": "西九条",
        "乗降客数": "59362"
    },
    {
        "順位": "308",
        "駅名": "ふじみ野",
        "乗降客数": "59305"
    },
    {
        "順位": "309",
        "駅名": "金沢文庫",
        "乗降客数": "58934"
    },
    {
        "順位": "310",
        "駅名": "蘇我",
        "乗降客数": "58924"
    },
    {
        "順位": "311",
        "駅名": "西新井",
        "乗降客数": "58836"
    },
    {
        "順位": "312",
        "駅名": "清瀬",
        "乗降客数": "58830"
    },
    {
        "順位": "313",
        "駅名": "豊田",
        "乗降客数": "58778"
    },
    {
        "順位": "314",
        "駅名": "小田原",
        "乗降客数": "58522"
    },
    {
        "順位": "315",
        "駅名": "新津田沼",
        "乗降客数": "58399"
    },
    {
        "順位": "316",
        "駅名": "横須賀中央",
        "乗降客数": "58202"
    },
    {
        "順位": "317",
        "駅名": "水天宮前",
        "乗降客数": "58180"
    },
    {
        "順位": "318",
        "駅名": "京都河原町",
        "乗降客数": "58113"
    },
    {
        "順位": "319",
        "駅名": "十三",
        "乗降客数": "57979"
    },
    {
        "順位": "320",
        "駅名": "南柏",
        "乗降客数": "57886"
    },
    {
        "順位": "321",
        "駅名": "鶴川",
        "乗降客数": "57563"
    },
    {
        "順位": "322",
        "駅名": "平井",
        "乗降客数": "57312"
    },
    {
        "順位": "323",
        "駅名": "西明石",
        "乗降客数": "57096"
    },
    {
        "順位": "324",
        "駅名": "池尻大橋",
        "乗降客数": "56812"
    },
    {
        "順位": "325",
        "駅名": "西中島南方",
        "乗降客数": "56702"
    },
    {
        "順位": "326",
        "駅名": "肥後橋",
        "乗降客数": "56535"
    },
    {
        "順位": "327",
        "駅名": "鷺沼",
        "乗降客数": "56498"
    },
    {
        "順位": "328",
        "駅名": "西八王子",
        "乗降客数": "55998"
    },
    {
        "順位": "329",
        "駅名": "町屋",
        "乗降客数": "55740"
    },
    {
        "順位": "330",
        "駅名": "元住吉",
        "乗降客数": "55514"
    },
    {
        "順位": "331",
        "駅名": "石川町",
        "乗降客数": "55458"
    },
    {
        "順位": "332",
        "駅名": "保土ヶ谷",
        "乗降客数": "55268"
    },
    {
        "順位": "333",
        "駅名": "東小金井",
        "乗降客数": "55210"
    },
    {
        "順位": "334",
        "駅名": "京成津田沼",
        "乗降客数": "54899"
    },
    {
        "順位": "335",
        "駅名": "草津",
        "乗降客数": "54892"
    },
    {
        "順位": "336",
        "駅名": "聖蹟桜ヶ丘",
        "乗降客数": "54749"
    },
    {
        "順位": "337",
        "駅名": "元町・中華街",
        "乗降客数": "54706"
    },
    {
        "順位": "338",
        "駅名": "垂水",
        "乗降客数": "54624"
    },
    {
        "順位": "339",
        "駅名": "高崎",
        "乗降客数": "54598"
    },
    {
        "順位": "340",
        "駅名": "金沢八景",
        "乗降客数": "54573"
    },
    {
        "順位": "341",
        "駅名": "国際展示場",
        "乗降客数": "54563"
    },
    {
        "順位": "342",
        "駅名": "南砂町",
        "乗降客数": "54476"
    },
    {
        "順位": "343",
        "駅名": "岐阜",
        "乗降客数": "54418"
    },
    {
        "順位": "344",
        "駅名": "京急蒲田",
        "乗降客数": "54259"
    },
    {
        "順位": "345",
        "駅名": "住道",
        "乗降客数": "54224"
    },
    {
        "順位": "346",
        "駅名": "船堀",
        "乗降客数": "53981"
    },
    {
        "順位": "347",
        "駅名": "港南台",
        "乗降客数": "53908"
    },
    {
        "順位": "348",
        "駅名": "水戸",
        "乗降客数": "53776"
    },
    {
        "順位": "349",
        "駅名": "保谷",
        "乗降客数": "53701"
    },
    {
        "順位": "350",
        "駅名": "我孫子",
        "乗降客数": "53636"
    },
    {
        "順位": "351",
        "駅名": "新長田",
        "乗降客数": "53568"
    },
    {
        "順位": "352",
        "駅名": "広尾",
        "乗降客数": "53479"
    },
    {
        "順位": "353",
        "駅名": "堺東",
        "乗降客数": "53412"
    },
    {
        "順位": "354",
        "駅名": "築地",
        "乗降客数": "53151"
    },
    {
        "順位": "355",
        "駅名": "矢場町",
        "乗降客数": "52826"
    },
    {
        "順位": "356",
        "駅名": "拝島",
        "乗降客数": "52628"
    },
    {
        "順位": "357",
        "駅名": "南大沢",
        "乗降客数": "52585"
    },
    {
        "順位": "358",
        "駅名": "藤が丘",
        "乗降客数": "52412"
    },
    {
        "順位": "359",
        "駅名": "センター南",
        "乗降客数": "52369"
    },
    {
        "順位": "360",
        "駅名": "越谷レイクタウン",
        "乗降客数": "52350"
    },
    {
        "順位": "361",
        "駅名": "東武練馬",
        "乗降客数": "52134"
    },
    {
        "順位": "362",
        "駅名": "福島",
        "乗降客数": "52108"
    },
    {
        "順位": "363",
        "駅名": "センター北",
        "乗降客数": "51969"
    },
    {
        "順位": "364",
        "駅名": "向ヶ丘遊園",
        "乗降客数": "51916"
    },
    {
        "順位": "365",
        "駅名": "千歳船橋",
        "乗降客数": "51828"
    },
    {
        "順位": "366",
        "駅名": "東浦和",
        "乗降客数": "51774"
    },
    {
        "順位": "367",
        "駅名": "相模原",
        "乗降客数": "51766"
    },
    {
        "順位": "368",
        "駅名": "甲子園",
        "乗降客数": "51646"
    },
    {
        "順位": "369",
        "駅名": "獨協大学前",
        "乗降客数": "51352"
    },
    {
        "順位": "370",
        "駅名": "鶴ヶ峰",
        "乗降客数": "51322"
    },
    {
        "順位": "371",
        "駅名": "刈谷",
        "乗降客数": "50894"
    },
    {
        "順位": "372",
        "駅名": "西国分寺",
        "乗降客数": "50840"
    },
    {
        "順位": "373",
        "駅名": "南草津",
        "乗降客数": "50766"
    },
    {
        "順位": "374",
        "駅名": "熊谷",
        "乗降客数": "50636"
    },
    {
        "順位": "375",
        "駅名": "成増",
        "乗降客数": "50573"
    },
    {
        "順位": "376",
        "駅名": "淡路町",
        "乗降客数": "50269"
    },
    {
        "順位": "377",
        "駅名": "高槻市",
        "乗降客数": "50262"
    },
    {
        "順位": "378",
        "駅名": "武蔵中原",
        "乗降客数": "50214"
    },
    {
        "順位": "379",
        "駅名": "瑞江",
        "乗降客数": "49991"
    },
    {
        "順位": "380",
        "駅名": "花小金井",
        "乗降客数": "49987"
    },
    {
        "順位": "381",
        "駅名": "三島",
        "乗降客数": "49868"
    },
    {
        "順位": "382",
        "駅名": "清澄白河",
        "乗降客数": "49852"
    },
    {
        "順位": "383",
        "駅名": "麹町",
        "乗降客数": "49806"
    },
    {
        "順位": "384",
        "駅名": "幕張本郷",
        "乗降客数": "49748"
    },
    {
        "順位": "385",
        "駅名": "初台",
        "乗降客数": "49640"
    },
    {
        "順位": "386",
        "駅名": "行徳",
        "乗降客数": "49562"
    },
    {
        "順位": "387",
        "駅名": "新神戸",
        "乗降客数": "49468"
    },
    {
        "順位": "388",
        "駅名": "小田急相模原",
        "乗降客数": "49416"
    },
    {
        "順位": "389",
        "駅名": "近鉄奈良",
        "乗降客数": "49225"
    },
    {
        "順位": "390",
        "駅名": "三ツ境",
        "乗降客数": "49177"
    },
    {
        "順位": "391",
        "駅名": "せんげん台",
        "乗降客数": "49089"
    },
    {
        "順位": "392",
        "駅名": "茨木市",
        "乗降客数": "49009"
    },
    {
        "順位": "393",
        "駅名": "東久留米",
        "乗降客数": "48688"
    },
    {
        "順位": "394",
        "駅名": "千種",
        "乗降客数": "48523"
    },
    {
        "順位": "395",
        "駅名": "上福岡",
        "乗降客数": "48471"
    },
    {
        "順位": "396",
        "駅名": "武蔵小山",
        "乗降客数": "48334"
    },
    {
        "順位": "397",
        "駅名": "天神橋筋六丁目",
        "乗降客数": "48255"
    },
    {
        "順位": "398",
        "駅名": "与野",
        "乗降客数": "48254"
    },
    {
        "順位": "399",
        "駅名": "新御徒町",
        "乗降客数": "48246"
    },
    {
        "順位": "400",
        "駅名": "逗子",
        "乗降客数": "48142"
    },
    {
        "順位": "401",
        "駅名": "六甲道",
        "乗降客数": "48082"
    },
    {
        "順位": "402",
        "駅名": "高幡不動",
        "乗降客数": "47988"
    },
    {
        "順位": "403",
        "駅名": "大倉山",
        "乗降客数": "47872"
    },
    {
        "順位": "404",
        "駅名": "高尾",
        "乗降客数": "47870"
    },
    {
        "順位": "405",
        "駅名": "京王稲田堤",
        "乗降客数": "47519"
    },
    {
        "順位": "406",
        "駅名": "本川越",
        "乗降客数": "47349"
    },
    {
        "順位": "407",
        "駅名": "芦屋",
        "乗降客数": "47334"
    },
    {
        "順位": "408",
        "駅名": "川西能勢口",
        "乗降客数": "47324"
    },
    {
        "順位": "409",
        "駅名": "上野御徒町",
        "乗降客数": "47215"
    },
    {
        "順位": "410",
        "駅名": "京王八王子",
        "乗降客数": "46932"
    },
    {
        "順位": "411",
        "駅名": "新宿西口",
        "乗降客数": "46745"
    },
    {
        "順位": "412",
        "駅名": "尾張一宮",
        "乗降客数": "46702"
    },
    {
        "順位": "413",
        "駅名": "南行徳",
        "乗降客数": "46441"
    },
    {
        "順位": "414",
        "駅名": "久屋大通",
        "乗降客数": "46258"
    },
    {
        "順位": "415",
        "駅名": "岩本町",
        "乗降客数": "45991"
    },
    {
        "順位": "416",
        "駅名": "新所沢",
        "乗降客数": "45869"
    },
    {
        "順位": "417",
        "駅名": "宝塚",
        "乗降客数": "45832"
    },
    {
        "順位": "418",
        "駅名": "長堀橋",
        "乗降客数": "45819"
    },
    {
        "順位": "419",
        "駅名": "江戸川橋",
        "乗降客数": "45773"
    },
    {
        "順位": "420",
        "駅名": "樟葉",
        "乗降客数": "45767"
    },
    {
        "順位": "421",
        "駅名": "勝田台",
        "乗降客数": "45600"
    },
    {
        "順位": "422",
        "駅名": "天満",
        "乗降客数": "45372"
    },
    {
        "順位": "423",
        "駅名": "越谷",
        "乗降客数": "45340"
    },
    {
        "順位": "424",
        "駅名": "福岡空港",
        "乗降客数": "45316"
    },
    {
        "順位": "425",
        "駅名": "妙典",
        "乗降客数": "45243"
    },
    {
        "順位": "426",
        "駅名": "新川崎",
        "乗降客数": "45222"
    },
    {
        "順位": "427",
        "駅名": "本郷三丁目",
        "乗降客数": "45151"
    },
    {
        "順位": "428",
        "駅名": "寝屋川市",
        "乗降客数": "45119"
    },
    {
        "順位": "429",
        "駅名": "名谷",
        "乗降客数": "45056"
    },
    {
        "順位": "430",
        "駅名": "上板橋",
        "乗降客数": "45028"
    },
    {
        "順位": "431",
        "駅名": "大正",
        "乗降客数": "44988"
    },
    {
        "順位": "432",
        "駅名": "京橋(東京)",
        "乗降客数": "44951"
    },
    {
        "順位": "433",
        "駅名": "北越谷",
        "乗降客数": "44841"
    },
    {
        "順位": "434",
        "駅名": "三国ヶ丘",
        "乗降客数": "44728"
    },
    {
        "順位": "435",
        "駅名": "泉中央",
        "乗降客数": "44672"
    },
    {
        "順位": "436",
        "駅名": "高蔵寺",
        "乗降客数": "44615"
    },
    {
        "順位": "437",
        "駅名": "鶴瀬",
        "乗降客数": "44606"
    },
    {
        "順位": "438",
        "駅名": "星ヶ丘",
        "乗降客数": "44602"
    },
    {
        "順位": "439",
        "駅名": "大久保",
        "乗降客数": "44558"
    },
    {
        "順位": "440",
        "駅名": "宮崎台",
        "乗降客数": "44470"
    },
    {
        "順位": "441",
        "駅名": "新八柱",
        "乗降客数": "44370"
    },
    {
        "順位": "442",
        "駅名": "都立大学",
        "乗降客数": "44353"
    },
    {
        "順位": "443",
        "駅名": "取手",
        "乗降客数": "44324"
    },
    {
        "順位": "444",
        "駅名": "地下鉄成増",
        "乗降客数": "44314"
    },
    {
        "順位": "445",
        "駅名": "大山",
        "乗降客数": "44307"
    },
    {
        "順位": "446",
        "駅名": "桶川",
        "乗降客数": "44298"
    },
    {
        "順位": "447",
        "駅名": "伊丹",
        "乗降客数": "44272"
    },
    {
        "順位": "448",
        "駅名": "馬橋",
        "乗降客数": "44232"
    },
    {
        "順位": "449",
        "駅名": "西宮",
        "乗降客数": "44228"
    },
    {
        "順位": "450",
        "駅名": "八潮",
        "乗降客数": "44200"
    },
    {
        "順位": "451",
        "駅名": "上前津",
        "乗降客数": "44170"
    },
    {
        "順位": "452",
        "駅名": "伊勢原",
        "乗降客数": "44098"
    },
    {
        "順位": "453",
        "駅名": "大阪天満宮",
        "乗降客数": "44028"
    },
    {
        "順位": "454",
        "駅名": "学園前",
        "乗降客数": "44017"
    },
    {
        "順位": "455",
        "駅名": "青砥",
        "乗降客数": "43907"
    },
    {
        "順位": "456",
        "駅名": "立花",
        "乗降客数": "43826"
    },
    {
        "順位": "457",
        "駅名": "稲田堤",
        "乗降客数": "43754"
    },
    {
        "順位": "458",
        "駅名": "馬喰町",
        "乗降客数": "43620"
    },
    {
        "順位": "459",
        "駅名": "昭島",
        "乗降客数": "43414"
    },
    {
        "順位": "460",
        "駅名": "小田急多摩センター",
        "乗降客数": "43358"
    },
    {
        "順位": "461",
        "駅名": "宮前平",
        "乗降客数": "43267"
    },
    {
        "順位": "462",
        "駅名": "森ノ宮",
        "乗降客数": "43116"
    },
    {
        "順位": "463",
        "駅名": "祖師ヶ谷大蔵",
        "乗降客数": "43037"
    },
    {
        "順位": "464",
        "駅名": "守谷",
        "乗降客数": "43000"
    },
    {
        "順位": "465",
        "駅名": "大和西大寺",
        "乗降客数": "42850"
    },
    {
        "順位": "466",
        "駅名": "加古川",
        "乗降客数": "42766"
    },
    {
        "順位": "467",
        "駅名": "日野",
        "乗降客数": "42746"
    },
    {
        "順位": "468",
        "駅名": "白山",
        "乗降客数": "42662"
    },
    {
        "順位": "469",
        "駅名": "生駒",
        "乗降客数": "42661"
    },
    {
        "順位": "470",
        "駅名": "南町田グランベリーパーク",
        "乗降客数": "42591"
    },
    {
        "順位": "471",
        "駅名": "東村山",
        "乗降客数": "42555"
    },
    {
        "順位": "472",
        "駅名": "香里園",
        "乗降客数": "42506"
    },
    {
        "順位": "473",
        "駅名": "武庫之荘",
        "乗降客数": "42433"
    },
    {
        "順位": "474",
        "駅名": "南船橋",
        "乗降客数": "42246"
    },
    {
        "順位": "475",
        "駅名": "鶯谷",
        "乗降客数": "42224"
    },
    {
        "順位": "476",
        "駅名": "阿波座",
        "乗降客数": "42176"
    },
    {
        "順位": "477",
        "駅名": "王寺",
        "乗降客数": "41972"
    },
    {
        "順位": "478",
        "駅名": "今池",
        "乗降客数": "41892"
    },
    {
        "順位": "479",
        "駅名": "川越市",
        "乗降客数": "41885"
    },
    {
        "順位": "480",
        "駅名": "吹田",
        "乗降客数": "41884"
    },
    {
        "順位": "481",
        "駅名": "狛江",
        "乗降客数": "41774"
    },
    {
        "順位": "482",
        "駅名": "東十条",
        "乗降客数": "41732"
    },
    {
        "順位": "483",
        "駅名": "下総中山",
        "乗降客数": "41694"
    },
    {
        "順位": "484",
        "駅名": "西新",
        "乗降客数": "41677"
    },
    {
        "順位": "485",
        "駅名": "大岡山",
        "乗降客数": "41367"
    },
    {
        "順位": "486",
        "駅名": "北小金",
        "乗降客数": "41352"
    },
    {
        "順位": "487",
        "駅名": "新鎌ヶ谷",
        "乗降客数": "41255"
    },
    {
        "順位": "488",
        "駅名": "祇園四条",
        "乗降客数": "41125"
    },
    {
        "順位": "489",
        "駅名": "宮原",
        "乗降客数": "41116"
    },
    {
        "順位": "490",
        "駅名": "八千代台",
        "乗降客数": "41077"
    },
    {
        "順位": "491",
        "駅名": "西神中央",
        "乗降客数": "41026"
    },
    {
        "順位": "492",
        "駅名": "生田",
        "乗降客数": "40976"
    },
    {
        "順位": "493",
        "駅名": "北戸田",
        "乗降客数": "40932"
    },
    {
        "順位": "494",
        "駅名": "愛甲石田",
        "乗降客数": "40799"
    },
    {
        "順位": "495",
        "駅名": "近鉄日本橋",
        "乗降客数": "40775"
    },
    {
        "順位": "496",
        "駅名": "ときわ台",
        "乗降客数": "40737"
    },
    {
        "順位": "497",
        "駅名": "古淵",
        "乗降客数": "40730"
    },
    {
        "順位": "498",
        "駅名": "北習志野",
        "乗降客数": "40551"
    },
    {
        "順位": "499",
        "駅名": "小手指",
        "乗降客数": "40509"
    },
    {
        "順位": "500",
        "駅名": "上新庄",
        "乗降客数": "40351"
    },
    {
        "順位": "501",
        "駅名": "立川北",
        "乗降客数": "40305"
    },
    {
        "順位": "502",
        "駅名": "近鉄丹波橋",
        "乗降客数": "39963"
    },
    {
        "順位": "503",
        "駅名": "石山",
        "乗降客数": "39880"
    },
    {
        "順位": "504",
        "駅名": "豊中",
        "乗降客数": "39769"
    },
    {
        "順位": "505",
        "駅名": "三ノ輪",
        "乗降客数": "39685"
    },
    {
        "順位": "506",
        "駅名": "岡崎",
        "乗降客数": "39677"
    },
    {
        "順位": "507",
        "駅名": "玉川学園前",
        "乗降客数": "39653"
    },
    {
        "順位": "508",
        "駅名": "名古屋城",
        "乗降客数": "39568"
    },
    {
        "順位": "509",
        "駅名": "兵庫",
        "乗降客数": "39530"
    },
    {
        "順位": "510",
        "駅名": "浮間舟渡",
        "乗降客数": "39514"
    },
    {
        "順位": "511",
        "駅名": "八柱",
        "乗降客数": "39437"
    },
    {
        "順位": "512",
        "駅名": "京王永山",
        "乗降客数": "39413"
    },
    {
        "順位": "513",
        "駅名": "金沢",
        "乗降客数": "39380"
    },
    {
        "順位": "514",
        "駅名": "新検見川",
        "乗降客数": "39354"
    },
    {
        "順位": "515",
        "駅名": "一之江",
        "乗降客数": "39354"
    },
    {
        "順位": "516",
        "駅名": "塚口",
        "乗降客数": "39335"
    },
    {
        "順位": "517",
        "駅名": "西馬込",
        "乗降客数": "39302"
    },
    {
        "順位": "518",
        "駅名": "麻布十番",
        "乗降客数": "39125"
    },
    {
        "順位": "519",
        "駅名": "新子安",
        "乗降客数": "39038"
    },
    {
        "順位": "520",
        "駅名": "平和島",
        "乗降客数": "38971"
    },
    {
        "順位": "521",
        "駅名": "西千葉",
        "乗降客数": "38812"
    },
    {
        "順位": "522",
        "駅名": "平和台",
        "乗降客数": "38769"
    },
    {
        "順位": "523",
        "駅名": "近鉄四日市",
        "乗降客数": "38628"
    },
    {
        "順位": "524",
        "駅名": "信濃町",
        "乗降客数": "38594"
    },
    {
        "順位": "525",
        "駅名": "京成上野",
        "乗降客数": "38573"
    },
    {
        "順位": "526",
        "駅名": "新座",
        "乗降客数": "38552"
    },
    {
        "順位": "527",
        "駅名": "戸田",
        "乗降客数": "38518"
    },
    {
        "順位": "528",
        "駅名": "東松戸",
        "乗降客数": "38434"
    },
    {
        "順位": "529",
        "駅名": "四街道",
        "乗降客数": "38352"
    },
    {
        "順位": "530",
        "駅名": "根岸",
        "乗降客数": "38304"
    },
    {
        "順位": "531",
        "駅名": "下高井戸",
        "乗降客数": "38221"
    },
    {
        "順位": "532",
        "駅名": "北松戸",
        "乗降客数": "38220"
    },
    {
        "順位": "533",
        "駅名": "新さっぽろ",
        "乗降客数": "38220"
    },
    {
        "順位": "534",
        "駅名": "御成門",
        "乗降客数": "38199"
    },
    {
        "順位": "535",
        "駅名": "つつじヶ丘",
        "乗降客数": "38162"
    },
    {
        "順位": "536",
        "駅名": "東池袋",
        "乗降客数": "38132"
    },
    {
        "順位": "537",
        "駅名": "上石神井",
        "乗降客数": "38002"
    },
    {
        "順位": "538",
        "駅名": "あおば通",
        "乗降客数": "37974"
    },
    {
        "順位": "539",
        "駅名": "四谷三丁目",
        "乗降客数": "37952"
    },
    {
        "順位": "540",
        "駅名": "瀬谷",
        "乗降客数": "37765"
    },
    {
        "順位": "541",
        "駅名": "摂津本山",
        "乗降客数": "37684"
    },
    {
        "順位": "542",
        "駅名": "小山",
        "乗降客数": "37678"
    },
    {
        "順位": "543",
        "駅名": "岸辺",
        "乗降客数": "37578"
    },
    {
        "順位": "544",
        "駅名": "玉川上水",
        "乗降客数": "37552"
    },
    {
        "順位": "545",
        "駅名": "東船橋",
        "乗降客数": "37490"
    },
    {
        "順位": "546",
        "駅名": "明大前",
        "乗降客数": "37476"
    },
    {
        "順位": "547",
        "駅名": "護国寺",
        "乗降客数": "37393"
    },
    {
        "順位": "548",
        "駅名": "池田",
        "乗降客数": "37312"
    },
    {
        "順位": "549",
        "駅名": "大橋",
        "乗降客数": "37294"
    },
    {
        "順位": "550",
        "駅名": "竹橋",
        "乗降客数": "37274"
    },
    {
        "順位": "551",
        "駅名": "八千代緑が丘",
        "乗降客数": "37239"
    },
    {
        "順位": "552",
        "駅名": "中津",
        "乗降客数": "37190"
    },
    {
        "順位": "553",
        "駅名": "北綾瀬",
        "乗降客数": "37167"
    },
    {
        "順位": "554",
        "駅名": "都賀",
        "乗降客数": "37118"
    },
    {
        "順位": "555",
        "駅名": "東京テレポート",
        "乗降客数": "37051"
    },
    {
        "順位": "556",
        "駅名": "稲毛海岸",
        "乗降客数": "37038"
    },
    {
        "順位": "557",
        "駅名": "千里丘",
        "乗降客数": "37026"
    },
    {
        "順位": "558",
        "駅名": "市が尾",
        "乗降客数": "36996"
    },
    {
        "順位": "559",
        "駅名": "京急久里浜",
        "乗降客数": "36859"
    },
    {
        "順位": "560",
        "駅名": "栄町",
        "乗降客数": "36726"
    },
    {
        "順位": "561",
        "駅名": "丹波橋",
        "乗降客数": "36713"
    },
    {
        "順位": "562",
        "駅名": "仲御徒町",
        "乗降客数": "36683"
    },
    {
        "順位": "563",
        "駅名": "地下鉄赤塚",
        "乗降客数": "36536"
    },
    {
        "順位": "564",
        "駅名": "鶴舞",
        "乗降客数": "36503"
    },
    {
        "順位": "565",
        "駅名": "みずほ台",
        "乗降客数": "36410"
    },
    {
        "順位": "566",
        "駅名": "篠崎",
        "乗降客数": "36382"
    },
    {
        "順位": "567",
        "駅名": "銀座一丁目",
        "乗降客数": "36285"
    },
    {
        "順位": "568",
        "駅名": "白楽",
        "乗降客数": "36184"
    },
    {
        "順位": "569",
        "駅名": "石橋阪大前",
        "乗降客数": "36184"
    },
    {
        "順位": "570",
        "駅名": "追浜",
        "乗降客数": "36171"
    },
    {
        "順位": "571",
        "駅名": "神楽坂",
        "乗降客数": "36048"
    },
    {
        "順位": "572",
        "駅名": "要町",
        "乗降客数": "36047"
    },
    {
        "順位": "573",
        "駅名": "久我山",
        "乗降客数": "36028"
    },
    {
        "順位": "574",
        "駅名": "桂",
        "乗降客数": "35998"
    },
    {
        "順位": "575",
        "駅名": "鎌取",
        "乗降客数": "35916"
    },
    {
        "順位": "576",
        "駅名": "JR難波",
        "乗降客数": "35860"
    },
    {
        "順位": "577",
        "駅名": "中村橋",
        "乗降客数": "35844"
    },
    {
        "順位": "578",
        "駅名": "麻生",
        "乗降客数": "35794"
    },
    {
        "順位": "579",
        "駅名": "高井戸",
        "乗降客数": "35673"
    },
    {
        "順位": "580",
        "駅名": "馬車道",
        "乗降客数": "35619"
    },
    {
        "順位": "581",
        "駅名": "旗の台",
        "乗降客数": "35613"
    },
    {
        "順位": "582",
        "駅名": "塚本",
        "乗降客数": "35612"
    },
    {
        "順位": "583",
        "駅名": "長野",
        "乗降客数": "35610"
    },
    {
        "順位": "584",
        "駅名": "光が丘",
        "乗降客数": "35365"
    },
    {
        "順位": "585",
        "駅名": "淡路",
        "乗降客数": "35332"
    },
    {
        "順位": "586",
        "駅名": "摂津富田",
        "乗降客数": "35274"
    },
    {
        "順位": "587",
        "駅名": "蓮田",
        "乗降客数": "35256"
    },
    {
        "順位": "588",
        "駅名": "十日市場",
        "乗降客数": "35222"
    },
    {
        "順位": "589",
        "駅名": "東新宿",
        "乗降客数": "35204"
    },
    {
        "順位": "590",
        "駅名": "狭山市",
        "乗降客数": "35140"
    },
    {
        "順位": "591",
        "駅名": "秦野",
        "乗降客数": "35053"
    },
    {
        "順位": "592",
        "駅名": "谷塚",
        "乗降客数": "35038"
    },
    {
        "順位": "593",
        "駅名": "薬院",
        "乗降客数": "35012"
    },
    {
        "順位": "594",
        "駅名": "沼津",
        "乗降客数": "34995"
    },
    {
        "順位": "595",
        "駅名": "リゾートゲートウェイ･ステーション",
        "乗降客数": "34974"
    },
    {
        "順位": "596",
        "駅名": "方南町",
        "乗降客数": "34927"
    },
    {
        "順位": "597",
        "駅名": "千川",
        "乗降客数": "34918"
    },
    {
        "順位": "598",
        "駅名": "東京ディズニーシー･ステーション",
        "乗降客数": "34916"
    },
    {
        "順位": "599",
        "駅名": "福山",
        "乗降客数": "34908"
    },
    {
        "順位": "600",
        "駅名": "八幡山",
        "乗降客数": "34899"
    },
    {
        "順位": "601",
        "駅名": "南与野",
        "乗降客数": "34856"
    },
    {
        "順位": "602",
        "駅名": "南茨木",
        "乗降客数": "34856"
    },
    {
        "順位": "603",
        "駅名": "鳳",
        "乗降客数": "34792"
    },
    {
        "順位": "604",
        "駅名": "氷川台",
        "乗降客数": "34762"
    },
    {
        "順位": "605",
        "駅名": "大口",
        "乗降客数": "34742"
    },
    {
        "順位": "606",
        "駅名": "洋光台",
        "乗降客数": "34732"
    },
    {
        "順位": "607",
        "駅名": "泉ヶ丘",
        "乗降客数": "34712"
    },
    {
        "順位": "608",
        "駅名": "乃木坂",
        "乗降客数": "34694"
    },
    {
        "順位": "609",
        "駅名": "上小田井",
        "乗降客数": "34657"
    },
    {
        "順位": "610",
        "駅名": "鹿児島中央",
        "乗降客数": "34642"
    },
    {
        "順位": "611",
        "駅名": "柏の葉キャンパス",
        "乗降客数": "34600"
    },
    {
        "順位": "612",
        "駅名": "布施",
        "乗降客数": "34546"
    },
    {
        "順位": "613",
        "駅名": "国会議事堂前",
        "乗降客数": "34496"
    },
    {
        "順位": "614",
        "駅名": "虎ノ門ヒルズ",
        "乗降客数": "34454"
    },
    {
        "順位": "615",
        "駅名": "梶が谷",
        "乗降客数": "34334"
    },
    {
        "順位": "616",
        "駅名": "蛍池",
        "乗降客数": "34222"
    },
    {
        "順位": "617",
        "駅名": "北赤羽",
        "乗降客数": "34182"
    },
    {
        "順位": "618",
        "駅名": "桃山台",
        "乗降客数": "33949"
    },
    {
        "順位": "619",
        "駅名": "本郷台",
        "乗降客数": "33922"
    },
    {
        "順位": "620",
        "駅名": "曙橋",
        "乗降客数": "33879"
    },
    {
        "順位": "621",
        "駅名": "相武台前",
        "乗降客数": "33753"
    },
    {
        "順位": "622",
        "駅名": "新富町",
        "乗降客数": "33659"
    },
    {
        "順位": "623",
        "駅名": "川西池田",
        "乗降客数": "33596"
    },
    {
        "順位": "624",
        "駅名": "近鉄八尾",
        "乗降客数": "33559"
    },
    {
        "順位": "625",
        "駅名": "蔵前",
        "乗降客数": "33542"
    },
    {
        "順位": "626",
        "駅名": "東岡崎",
        "乗降客数": "33508"
    },
    {
        "順位": "627",
        "駅名": "多摩センター",
        "乗降客数": "33450"
    },
    {
        "順位": "628",
        "駅名": "鴻巣",
        "乗降客数": "33450"
    },
    {
        "順位": "629",
        "駅名": "小伝馬町",
        "乗降客数": "33442"
    },
    {
        "順位": "630",
        "駅名": "長岡京",
        "乗降客数": "33406"
    },
    {
        "順位": "631",
        "駅名": "上永谷",
        "乗降客数": "33399"
    },
    {
        "順位": "632",
        "駅名": "堺",
        "乗降客数": "33348"
    },
    {
        "順位": "633",
        "駅名": "五井",
        "乗降客数": "33277"
    },
    {
        "順位": "634",
        "駅名": "磯子",
        "乗降客数": "33260"
    },
    {
        "順位": "635",
        "駅名": "西院",
        "乗降客数": "33247"
    },
    {
        "順位": "636",
        "駅名": "学園都市",
        "乗降客数": "33186"
    },
    {
        "順位": "637",
        "駅名": "小平",
        "乗降客数": "33184"
    },
    {
        "順位": "638",
        "駅名": "五反野",
        "乗降客数": "33151"
    },
    {
        "順位": "639",
        "駅名": "甲子園口",
        "乗降客数": "33130"
    },
    {
        "順位": "640",
        "駅名": "北柏",
        "乗降客数": "33120"
    },
    {
        "順位": "641",
        "駅名": "藤井寺",
        "乗降客数": "33114"
    },
    {
        "順位": "642",
        "駅名": "倉敷",
        "乗降客数": "33022"
    },
    {
        "順位": "643",
        "駅名": "池上",
        "乗降客数": "32969"
    },
    {
        "順位": "644",
        "駅名": "西早稲田",
        "乗降客数": "32955"
    },
    {
        "順位": "645",
        "駅名": "瀬田",
        "乗降客数": "32884"
    },
    {
        "順位": "646",
        "駅名": "岩槻",
        "乗降客数": "32821"
    },
    {
        "順位": "647",
        "駅名": "久宝寺",
        "乗降客数": "32766"
    },
    {
        "順位": "648",
        "駅名": "成瀬",
        "乗降客数": "32738"
    },
    {
        "順位": "649",
        "駅名": "矢向",
        "乗降客数": "32696"
    },
    {
        "順位": "650",
        "駅名": "京成大久保",
        "乗降客数": "32694"
    },
    {
        "順位": "651",
        "駅名": "今津",
        "乗降客数": "32664"
    },
    {
        "順位": "652",
        "駅名": "板橋本町",
        "乗降客数": "32635"
    },
    {
        "順位": "653",
        "駅名": "若葉",
        "乗降客数": "32619"
    },
    {
        "順位": "654",
        "駅名": "大和八木",
        "乗降客数": "32591"
    },
    {
        "順位": "655",
        "駅名": "八王子みなみ野",
        "乗降客数": "32578"
    },
    {
        "順位": "656",
        "駅名": "中洲川端",
        "乗降客数": "32558"
    },
    {
        "順位": "657",
        "駅名": "白金高輪",
        "乗降客数": "32521"
    },
    {
        "順位": "658",
        "駅名": "湯島",
        "乗降客数": "32511"
    },
    {
        "順位": "659",
        "駅名": "船橋法典",
        "乗降客数": "32488"
    },
    {
        "順位": "660",
        "駅名": "東海大学前",
        "乗降客数": "32462"
    },
    {
        "順位": "661",
        "駅名": "梅島",
        "乗降客数": "32421"
    },
    {
        "順位": "662",
        "駅名": "四条畷",
        "乗降客数": "32356"
    },
    {
        "順位": "663",
        "駅名": "守山",
        "乗降客数": "32206"
    },
    {
        "順位": "664",
        "駅名": "大津",
        "乗降客数": "32150"
    },
    {
        "順位": "665",
        "駅名": "桃谷",
        "乗降客数": "32132"
    },
    {
        "順位": "666",
        "駅名": "丸の内",
        "乗降客数": "32126"
    },
    {
        "順位": "667",
        "駅名": "新日本橋",
        "乗降客数": "32072"
    },
    {
        "順位": "668",
        "駅名": "京成八幡",
        "乗降客数": "32061"
    },
    {
        "順位": "669",
        "駅名": "京成立石",
        "乗降客数": "32060"
    },
    {
        "順位": "670",
        "駅名": "津",
        "乗降客数": "32051"
    },
    {
        "順位": "671",
        "駅名": "東三国",
        "乗降客数": "32031"
    },
    {
        "順位": "672",
        "駅名": "柿生",
        "乗降客数": "31978"
    },
    {
        "順位": "673",
        "駅名": "新高円寺",
        "乗降客数": "31901"
    },
    {
        "順位": "674",
        "駅名": "王子神谷",
        "乗降客数": "31896"
    },
    {
        "順位": "675",
        "駅名": "西大井",
        "乗降客数": "31864"
    },
    {
        "順位": "676",
        "駅名": "長居",
        "乗降客数": "31853"
    },
    {
        "順位": "677",
        "駅名": "駒場東大前",
        "乗降客数": "31775"
    },
    {
        "順位": "678",
        "駅名": "放出",
        "乗降客数": "31766"
    },
    {
        "順位": "679",
        "駅名": "さがみ野",
        "乗降客数": "31752"
    },
    {
        "順位": "680",
        "駅名": "国領",
        "乗降客数": "31746"
    },
    {
        "順位": "681",
        "駅名": "入谷",
        "乗降客数": "31731"
    },
    {
        "順位": "682",
        "駅名": "桜上水",
        "乗降客数": "31663"
    },
    {
        "順位": "683",
        "駅名": "山手",
        "乗降客数": "31370"
    },
    {
        "順位": "684",
        "駅名": "寺田町",
        "乗降客数": "31362"
    },
    {
        "順位": "685",
        "駅名": "吉川",
        "乗降客数": "31308"
    },
    {
        "順位": "686",
        "駅名": "板橋区役所前",
        "乗降客数": "31287"
    },
    {
        "順位": "687",
        "駅名": "北本",
        "乗降客数": "31176"
    },
    {
        "順位": "688",
        "駅名": "京成成田",
        "乗降客数": "31140"
    },
    {
        "順位": "689",
        "駅名": "和泉府中",
        "乗降客数": "31002"
    },
    {
        "順位": "690",
        "駅名": "名鉄一宮",
        "乗降客数": "30989"
    },
    {
        "順位": "691",
        "駅名": "南千住",
        "乗降客数": "30962"
    },
    {
        "順位": "692",
        "駅名": "大日",
        "乗降客数": "30932"
    },
    {
        "順位": "693",
        "駅名": "新中野",
        "乗降客数": "30917"
    },
    {
        "順位": "694",
        "駅名": "灘",
        "乗降客数": "30904"
    },
    {
        "順位": "695",
        "駅名": "大分",
        "乗降客数": "30854"
    },
    {
        "順位": "696",
        "駅名": "舞子",
        "乗降客数": "30848"
    },
    {
        "順位": "697",
        "駅名": "鹿島田",
        "乗降客数": "30816"
    },
    {
        "順位": "698",
        "駅名": "天王台",
        "乗降客数": "30780"
    },
    {
        "順位": "699",
        "駅名": "勝川",
        "乗降客数": "30770"
    },
    {
        "順位": "700",
        "駅名": "青物横丁",
        "乗降客数": "30748"
    },
    {
        "順位": "701",
        "駅名": "千葉みなと",
        "乗降客数": "30708"
    },
    {
        "順位": "702",
        "駅名": "松本",
        "乗降客数": "30663"
    },
    {
        "順位": "703",
        "駅名": "奈良",
        "乗降客数": "30606"
    },
    {
        "順位": "704",
        "駅名": "玉造",
        "乗降客数": "30596"
    },
    {
        "順位": "705",
        "駅名": "長後",
        "乗降客数": "30546"
    },
    {
        "順位": "706",
        "駅名": "西18丁目",
        "乗降客数": "30402"
    },
    {
        "順位": "707",
        "駅名": "南方",
        "乗降客数": "30280"
    },
    {
        "順位": "708",
        "駅名": "杉田",
        "乗降客数": "30217"
    },
    {
        "順位": "709",
        "駅名": "神宮前",
        "乗降客数": "30214"
    },
    {
        "順位": "710",
        "駅名": "近江八幡",
        "乗降客数": "30186"
    },
    {
        "順位": "711",
        "駅名": "江田",
        "乗降客数": "30177"
    },
    {
        "順位": "712",
        "駅名": "勾当台公園",
        "乗降客数": "30154"
    },
    {
        "順位": "713",
        "駅名": "緑地公園",
        "乗降客数": "30127"
    },
    {
        "順位": "714",
        "駅名": "大国町",
        "乗降客数": "30126"
    },
    {
        "順位": "715",
        "駅名": "梅ヶ丘",
        "乗降客数": "30091"
    },
    {
        "順位": "716",
        "駅名": "大垣",
        "乗降客数": "30067"
    },
    {
        "順位": "717",
        "駅名": "名鉄岐阜",
        "乗降客数": "30058"
    },
    {
        "順位": "718",
        "駅名": "和歌山",
        "乗降客数": "30038"
    },
    {
        "順位": "719",
        "駅名": "高の原",
        "乗降客数": "30014"
    },
    {
        "順位": "720",
        "駅名": "つくば",
        "乗降客数": "30000"
    },
    {
        "順位": "721",
        "駅名": "読売ランド前",
        "乗降客数": "29962"
    },
    {
        "順位": "722",
        "駅名": "野田",
        "乗降客数": "29895"
    },
    {
        "順位": "723",
        "駅名": "都島",
        "乗降客数": "29880"
    },
    {
        "順位": "724",
        "駅名": "希望ヶ丘",
        "乗降客数": "29877"
    },
    {
        "順位": "725",
        "駅名": "立川南",
        "乗降客数": "29866"
    },
    {
        "順位": "726",
        "駅名": "内幸町",
        "乗降客数": "29846"
    },
    {
        "順位": "727",
        "駅名": "谷町六丁目",
        "乗降客数": "29818"
    },
    {
        "順位": "728",
        "駅名": "三条",
        "乗降客数": "29803"
    },
    {
        "順位": "729",
        "駅名": "出町柳",
        "乗降客数": "29796"
    },
    {
        "順位": "730",
        "駅名": "東高円寺",
        "乗降客数": "29765"
    },
    {
        "順位": "731",
        "駅名": "下丸子",
        "乗降客数": "29684"
    },
    {
        "順位": "732",
        "駅名": "妙法寺",
        "乗降客数": "29646"
    },
    {
        "順位": "733",
        "駅名": "北大路",
        "乗降客数": "29524"
    },
    {
        "順位": "734",
        "駅名": "六町",
        "乗降客数": "29500"
    },
    {
        "順位": "735",
        "駅名": "西大路",
        "乗降客数": "29488"
    },
    {
        "順位": "736",
        "駅名": "西小山",
        "乗降客数": "29454"
    },
    {
        "順位": "737",
        "駅名": "お花茶屋",
        "乗降客数": "29420"
    },
    {
        "順位": "738",
        "駅名": "南林間",
        "乗降客数": "29406"
    },
    {
        "順位": "739",
        "駅名": "厚木",
        "乗降客数": "29357"
    },
    {
        "順位": "740",
        "駅名": "羽沢横浜国大",
        "乗降客数": "29336"
    },
    {
        "順位": "741",
        "駅名": "中央大学・明星大学",
        "乗降客数": "29320"
    },
    {
        "順位": "742",
        "駅名": "西11丁目",
        "乗降客数": "29276"
    },
    {
        "順位": "743",
        "駅名": "桜ノ宮",
        "乗降客数": "29270"
    },
    {
        "順位": "744",
        "駅名": "仲町台",
        "乗降客数": "29222"
    },
    {
        "順位": "745",
        "駅名": "千駄ヶ谷",
        "乗降客数": "29220"
    },
    {
        "順位": "746",
        "駅名": "盛岡",
        "乗降客数": "29220"
    },
    {
        "順位": "747",
        "駅名": "和泉中央",
        "乗降客数": "29130"
    },
    {
        "順位": "748",
        "駅名": "横川",
        "乗降客数": "29124"
    },
    {
        "順位": "749",
        "駅名": "北野田",
        "乗降客数": "29087"
    },
    {
        "順位": "750",
        "駅名": "喜多見",
        "乗降客数": "29015"
    },
    {
        "順位": "751",
        "駅名": "品川シーサイド",
        "乗降客数": "28947"
    },
    {
        "順位": "752",
        "駅名": "久米川",
        "乗降客数": "28861"
    },
    {
        "順位": "753",
        "駅名": "大島",
        "乗降客数": "28834"
    },
    {
        "順位": "754",
        "駅名": "新栄町",
        "乗降客数": "28816"
    },
    {
        "順位": "755",
        "駅名": "能見台",
        "乗降客数": "28786"
    },
    {
        "順位": "756",
        "駅名": "江古田",
        "乗降客数": "28785"
    },
    {
        "順位": "757",
        "駅名": "入間市",
        "乗降客数": "28740"
    },
    {
        "順位": "758",
        "駅名": "田園調布",
        "乗降客数": "28655"
    },
    {
        "順位": "759",
        "駅名": "竹田",
        "乗降客数": "28638"
    },
    {
        "順位": "760",
        "駅名": "郡山",
        "乗降客数": "28620"
    },
    {
        "順位": "761",
        "駅名": "知立",
        "乗降客数": "28591"
    },
    {
        "順位": "762",
        "駅名": "東所沢",
        "乗降客数": "28562"
    },
    {
        "順位": "763",
        "駅名": "桂川",
        "乗降客数": "28540"
    },
    {
        "順位": "764",
        "駅名": "八事",
        "乗降客数": "28462"
    },
    {
        "順位": "765",
        "駅名": "住之江公園",
        "乗降客数": "28453"
    },
    {
        "順位": "766",
        "駅名": "谷上",
        "乗降客数": "28428"
    },
    {
        "順位": "767",
        "駅名": "西鉄久留米",
        "乗降客数": "28355"
    },
    {
        "順位": "768",
        "駅名": "京急鶴見",
        "乗降客数": "28323"
    },
    {
        "順位": "769",
        "駅名": "四ツ橋",
        "乗降客数": "28297"
    },
    {
        "順位": "770",
        "駅名": "幕張",
        "乗降客数": "28226"
    },
    {
        "順位": "771",
        "駅名": "鶴ヶ島",
        "乗降客数": "28197"
    },
    {
        "順位": "772",
        "駅名": "千石",
        "乗降客数": "28140"
    },
    {
        "順位": "773",
        "駅名": "鷺ノ宮",
        "乗降客数": "28112"
    },
    {
        "順位": "774",
        "駅名": "府中本町",
        "乗降客数": "28108"
    },
    {
        "順位": "775",
        "駅名": "熊本",
        "乗降客数": "28092"
    },
    {
        "順位": "776",
        "駅名": "永福町",
        "乗降客数": "28086"
    },
    {
        "順位": "777",
        "駅名": "魚崎",
        "乗降客数": "28066"
    },
    {
        "順位": "778",
        "駅名": "吉塚",
        "乗降客数": "28034"
    },
    {
        "順位": "779",
        "駅名": "志村三丁目",
        "乗降客数": "28004"
    },
    {
        "順位": "780",
        "駅名": "三郷中央",
        "乗降客数": "28000"
    },
    {
        "順位": "781",
        "駅名": "京成千葉",
        "乗降客数": "27978"
    },
    {
        "順位": "782",
        "駅名": "小作",
        "乗降客数": "27972"
    },
    {
        "順位": "783",
        "駅名": "祐天寺",
        "乗降客数": "27927"
    },
    {
        "順位": "784",
        "駅名": "尾山台",
        "乗降客数": "27916"
    },
    {
        "順位": "785",
        "駅名": "雑色",
        "乗降客数": "27889"
    },
    {
        "順位": "786",
        "駅名": "二重橋前",
        "乗降客数": "27886"
    },
    {
        "順位": "787",
        "駅名": "新千歳空港",
        "乗降客数": "27870"
    },
    {
        "順位": "788",
        "駅名": "幡ヶ谷",
        "乗降客数": "27850"
    },
    {
        "順位": "789",
        "駅名": "動物園前",
        "乗降客数": "27808"
    },
    {
        "順位": "790",
        "駅名": "都庁前",
        "乗降客数": "27800"
    },
    {
        "順位": "791",
        "駅名": "土呂",
        "乗降客数": "27762"
    },
    {
        "順位": "792",
        "駅名": "検見川浜",
        "乗降客数": "27740"
    },
    {
        "順位": "793",
        "駅名": "福生",
        "乗降客数": "27684"
    },
    {
        "順位": "794",
        "駅名": "武蔵関",
        "乗降客数": "27659"
    },
    {
        "順位": "795",
        "駅名": "東大島",
        "乗降客数": "27592"
    },
    {
        "順位": "796",
        "駅名": "成田",
        "乗降客数": "27562"
    },
    {
        "順位": "797",
        "駅名": "東武動物公園",
        "乗降客数": "27558"
    },
    {
        "順位": "798",
        "駅名": "河内松原",
        "乗降客数": "27550"
    },
    {
        "順位": "799",
        "駅名": "北上尾",
        "乗降客数": "27468"
    },
    {
        "順位": "800",
        "駅名": "本山",
        "乗降客数": "27450"
    },
    {
        "順位": "801",
        "駅名": "与野本町",
        "乗降客数": "27414"
    },
    {
        "順位": "802",
        "駅名": "新田",
        "乗降客数": "27339"
    },
    {
        "順位": "803",
        "駅名": "田原町",
        "乗降客数": "27273"
    },
    {
        "順位": "804",
        "駅名": "汐留",
        "乗降客数": "27203"
    },
    {
        "順位": "805",
        "駅名": "京王堀之内",
        "乗降客数": "27194"
    },
    {
        "順位": "806",
        "駅名": "春日井",
        "乗降客数": "27191"
    },
    {
        "順位": "807",
        "駅名": "長瀬",
        "乗降客数": "27088"
    },
    {
        "順位": "808",
        "駅名": "志村坂上",
        "乗降客数": "27062"
    },
    {
        "順位": "809",
        "駅名": "鶴間",
        "乗降客数": "27031"
    },
    {
        "順位": "810",
        "駅名": "六会日大前",
        "乗降客数": "26972"
    },
    {
        "順位": "811",
        "駅名": "星川",
        "乗降客数": "26934"
    },
    {
        "順位": "812",
        "駅名": "不動前",
        "乗降客数": "26931"
    },
    {
        "順位": "813",
        "駅名": "折尾",
        "乗降客数": "26902"
    },
    {
        "順位": "814",
        "駅名": "宮の沢",
        "乗降客数": "26838"
    },
    {
        "順位": "815",
        "駅名": "福住",
        "乗降客数": "26836"
    },
    {
        "順位": "816",
        "駅名": "円山公園",
        "乗降客数": "26768"
    },
    {
        "順位": "817",
        "駅名": "豊田市",
        "乗降客数": "26744"
    },
    {
        "順位": "818",
        "駅名": "琴似",
        "乗降客数": "26730"
    },
    {
        "順位": "819",
        "駅名": "天王洲アイル",
        "乗降客数": "26691"
    },
    {
        "順位": "820",
        "駅名": "土浦",
        "乗降客数": "26686"
    },
    {
        "順位": "821",
        "駅名": "若松河田",
        "乗降客数": "26565"
    },
    {
        "順位": "822",
        "駅名": "小田急永山",
        "乗降客数": "26493"
    },
    {
        "順位": "823",
        "駅名": "高津",
        "乗降客数": "26470"
    },
    {
        "順位": "824",
        "駅名": "西巣鴨",
        "乗降客数": "26467"
    },
    {
        "順位": "825",
        "駅名": "西浦和",
        "乗降客数": "26466"
    },
    {
        "順位": "826",
        "駅名": "金剛",
        "乗降客数": "26466"
    },
    {
        "順位": "827",
        "駅名": "曳舟",
        "乗降客数": "26427"
    },
    {
        "順位": "828",
        "駅名": "飯能",
        "乗降客数": "26414"
    },
    {
        "順位": "829",
        "駅名": "新三郷",
        "乗降客数": "26394"
    },
    {
        "順位": "830",
        "駅名": "坂戸",
        "乗降客数": "26296"
    }
]
